toadie/__init__.py
toadie/toadie.py
toadie/lib/__init__.py
toadie/lib/components.py
toadie/lib/dependencies.py
toadie-0.1.1a1.dist-info/DESCRIPTION.rst
toadie-0.1.1a1.dist-info/METADATA
toadie-0.1.1a1.dist-info/RECORD
toadie-0.1.1a1.dist-info/WHEEL
toadie-0.1.1a1.dist-info/entry_points.txt
toadie-0.1.1a1.dist-info/metadata.json
toadie-0.1.1a1.dist-info/top_level.txt
