Metadata-Version: 2.0
Name: toadie
Version: 0.1.1a1
Summary: Command line interface for development of microservices with the ambassador pattern.
Home-page: UNKNOWN
Author: David 'Gonzo' Gonzalez
Author-email: davidbgonzalez@gmail.com
License: Apache Software License
Keywords: docker,microservices
Platform: UNKNOWN
Classifier: Development Status :: 3 - Alpha
Classifier: Intended Audience :: Developers
Classifier: Topic :: Software Development :: Build Tools
Classifier: License :: OSI Approved :: Apache Software License
Classifier: Programming Language :: Python :: 2.7
Classifier: Programming Language :: Python :: 3
Classifier: Programming Language :: Python :: 3.2
Classifier: Programming Language :: Python :: 3.3
Classifier: Programming Language :: Python :: 3.4
Requires-Dist: PyYAML (>=3.11)
Requires-Dist: click (>=6.3)
Requires-Dist: honcho (>=0.6.6)
